[
    {
        "timestamp": 1715449503439,
        "blockIndex": 1,
        "previousBlockHash": "0",
        "currentBlockHash": "0",
        "data": []
    },
    {
        "timestamp": 1715449544363,
        "blockIndex": 2,
        "previousBlockHash": "0",
        "currentBlockHash": "e48eec2535ba6b0c12cbd3f161604e4865cd786d54f7601e1c028eddbdbc3f75",
        "data": {
            "position": {
                "longitude": 123,
                "latitude": 456
            }
        }
    },
    {
        "timestamp": 1715449564393,
        "blockIndex": 3,
        "previousBlockHash": "e48eec2535ba6b0c12cbd3f161604e4865cd786d54f7601e1c028eddbdbc3f75",
        "currentBlockHash": "92dfce31c3591e4f5a520260bd8dd4bf4b33b2d37d8eee37079d9cbe49db4870",
        "data": {
            "position": {
                "longitude": 123,
                "latitude": 456
            }
        }
    },
    {
        "timestamp": 1715449998520,
        "blockIndex": 4,
        "previousBlockHash": "92dfce31c3591e4f5a520260bd8dd4bf4b33b2d37d8eee37079d9cbe49db4870",
        "currentBlockHash": "ee25ee69246f5a9af6309d007ac4163fbc9d22eeef277a66a314490840b4b120",
        "data": {
            "position": {
                "longitude": 123,
                "latitude": 456
            }
        }
    }
]